[
    {
        "uuid": "4cc650a2-75dc-3230-a8a9-18f93b39f894",
        "photo": "http:\/\/lorempixel.com\/640\/480\/people\/?87899",
        "name": "Alisa",
        "lastName": "Kuhic",
        "description": "Cupiditate autem illum unde veritatis quos vel. Modi deserunt nostrum ab necessitatibus qui quas odio debitis.",
        "phoneNumbers": ["621-950-9880", "+06(4)6249015049", "410.072.5346x817"],
        "emails": ["bWisozk@Rodriguez.com", "bCorwin@gmail.com", "Rolfson.Stephon@yahoo.com"],
        "addersses": [{
                "name": "67693 Franecki Mission\nHoppeton, MA 23876",
                "city": "New Emmet",
                "latitude": -63.124735,
                "longitude": -16.265088
            }, {
                "name": "298 Donna Valleys Suite 682\nSouth Jacintheport, VA 39501",
                "city": "South Lamarport",
                "latitude": -69.992482,
                "longitude": 42.347811
            }]
    },
    {
        "uuid": "4a2fe570-2de8-3841-a952-e154f322d609",
        "photo": "http:\/\/lorempixel.com\/640\/480\/people\/?61014",
        "name": "Laurine",
        "lastName": "Feil",
        "description": "Corporis facere consequatur quam optio tempore soluta. Odit sit amet possimus neque exercitationem. Consequatur voluptatem ut libero maxime.",
        "phoneNumbers": ["1-656-677-5513", "(790)298-7307", "1-479-723-5719x756"],
        "emails": ["Justina.Bauch@Breitenberg.com", "Dave44@hotmail.com", "Schaefer.Elena@yahoo.com"],
        "addersses": [{
                "name": "98758 Roman Lights\nJohnsmouth, IN 32229-8403",
                "city": "Lake Marietta",
                "latitude": -45.406572,
                "longitude": -178.439004
            }, {
                "name": "81449 Glen Ridges Suite 638\nErikaland, IA 41173-2688",
                "city": "East Roselyn",
                "latitude": -70.300279,
                "longitude": -123.569062
            }]
    },
    {
        "uuid": "f2e02d72-a51f-3a40-879e-465d1da3cb4d",
        "photo": "http:\/\/lorempixel.com\/640\/480\/people\/?41154",
        "name": "Cora",
        "lastName": "Walker",
        "description": "Qui itaque dolores perspiciatis tempora error id fugiat. Aspernatur possimus quidem ea excepturi culpa sunt. Unde blanditiis qui labore culpa laboriosam sapiente.",
        "phoneNumbers": ["1-443-799-3445", "996.904.8843", "05345176101"],
        "emails": ["fHilpert@Kuhic.com", "Toy.Bridie@Hintz.net", "Kunze.Itzel@gmail.com"],
        "addersses": [{
                "name": "092 Dietrich Burg Suite 603\nWest Talon, KS 80621-8181",
                "city": "Breitenbergport",
                "latitude": 72.548886,
                "longitude": 179.714086
            }, {
                "name": "0008 Alexandro Shore\nHodkiewiczland, NC 11489-8935",
                "city": "Port Keirashire",
                "latitude": 73.119767,
                "longitude": 145.455499
            }]
    },
    {
        "uuid": "d0daaeb2-b678-3c14-a8fe-50a5c70cff0e",
        "photo": "http:\/\/lorempixel.com\/640\/480\/people\/?42523",
        "name": "Margarett",
        "lastName": "Howell",
        "description": "Aperiam quisquam qui at. Deserunt amet alias rem alias. Rerum eveniet voluptatum deleniti voluptatem. Omnis et molestiae autem accusamus rerum.",
        "phoneNumbers": ["03785145121", "217-285-3819x80239", "470-903-4089"],
        "emails": ["Clyde.Morar@yahoo.com", "Osinski.Adolfo@gmail.com", "Jayda.Harris@hotmail.com"],
        "addersses": [{
                "name": "441 Abernathy Viaduct\nEast Jarret, NJ 29349",
                "city": "Lake Adonis",
                "latitude": 36.512533,
                "longitude": 18.064044
            }, {
                "name": "0266 Tromp Shore Apt. 533\nDuBuquefurt, GA 82151",
                "city": "Johannchester",
                "latitude": -8.078527,
                "longitude": -91.404391
            }]
    },
    {
        "uuid": "f5b2b547-e5e3-36d0-bb4a-67f954256c1a",
        "photo": "http:\/\/lorempixel.com\/640\/480\/people\/?89473",
        "name": "Erica",
        "lastName": "Zboncak",
        "description": "Sapiente dolor culpa laborum sunt maiores voluptate aut minima. Odio sed qui amet nam sed sed dicta. Est repellendus mollitia commodi et aliquam. In dolorem fugiat qui nostrum autem. Accusantium eos quis asperiores rem harum laudantium minus enim.",
        "phoneNumbers": ["095.132.7418x995", "052.998.6822x36304", "1-775-316-4389x01054"],
        "emails": ["mKoss@gmail.com", "cErnser@Price.net", "Weissnat.Lura@Klocko.com"],
        "addersses": [{
                "name": "00427 Haag Cove Apt. 771\nAlysashire, CO 70358",
                "city": "Alvertafort",
                "latitude": 84.234243,
                "longitude": -37.735437
            }, {
                "name": "8720 Alysa Mount Suite 879\nNicolasborough, NV 77101",
                "city": "Altabury",
                "latitude": 71.343351,
                "longitude": -130.014579
            }]
    },
    {
        "uuid": "c3af55f5-bf17-3597-83ae-439bafc2421a",
        "photo": "http:\/\/lorempixel.com\/640\/480\/people\/?52747",
        "name": "Joesph",
        "lastName": "Walsh",
        "description": "Quasi labore sit molestiae necessitatibus ut ratione perferendis. Aspernatur eveniet quaerat qui rerum reiciendis enim.",
        "phoneNumbers": ["211.292.8230x753", "1-908-999-1891x28639", "972.796.1037x14597"],
        "emails": ["August39@hotmail.com", "rProsacco@yahoo.com", "Isaiah72@Rolfson.com"],
        "addersses": [{
                "name": "913 Farrell Vista Suite 330\nNorth Jeaniefort, AL 35781",
                "city": "West Rosario",
                "latitude": -30.042924,
                "longitude": 100.165243
            }, {
                "name": "5527 Eloise Ford Apt. 665\nJamisontown, MI 86274",
                "city": "Cormiertown",
                "latitude": -22.023881,
                "longitude": 154.375435
            }]
    },
    {
        "uuid": "e5601dd2-db19-390b-bee6-81c798ff704f",
        "photo": "http:\/\/lorempixel.com\/640\/480\/people\/?16072",
        "name": "Vivian",
        "lastName": "Predovic",
        "description": "Aut fuga eum est libero est debitis voluptatum. Expedita nesciunt ab qui doloremque praesentium. Vitae esse in commodi aut harum nihil quibusdam tenetur.",
        "phoneNumbers": ["1-398-924-9607", "1-806-044-9547x7431", "1-526-805-6791"],
        "emails": ["Esta56@gmail.com", "Adan34@Moore.com", "Cleveland.Fadel@Bailey.com"],
        "addersses": [{
                "name": "989 Nash Bypass\nConsidinetown, TN 93226",
                "city": "North Lydia",
                "latitude": 68.255443,
                "longitude": 105.565139
            }, {
                "name": "2569 Hillary Ridges Suite 345\nPort Emery, MN 76653-6213",
                "city": "Mafaldaport",
                "latitude": 37.112,
                "longitude": 149.00947
            }]
    }
]